{
    "icon": "ru.svg",
    "params":
        {
            "dashboard": "Рабочий стол",
            "contracts": "Сделки",
            "customers": "Покупатели",
            "tasks": "Задачи",
            "lists": "Списки",
            "mail": "Почта",
            "bi": "Аналитика",
            "settings": "Настройки",
            "contacts": "Контакты",
            "search": "Поиск и фильтр",
            "events": "События",
            "addcontract": "Новая сделка",
            "addcompany": "Добавить компанию",
            "addcontact": "Добавить контакт",
            "addtask": "Добавить задачу",
            "addfile": "Добавить файл",
            "write": "Написать",
            "save": "Сохранить",
            "onweek": "за неделю",
            "newTasks": "задачи к выполнению",
            "completeTasks": "выполненные задачи",
            "withoutTask": "сделок без задач",
            "overdueTasks": "просроченные задачи",
            "execution_date": "дата исполнения",
            "responsible": "Ответственный",
            "object": "объект",
            "taskType": "тип задачи",
            "taskDescription": "текст задачи",
            "result": "результат",
            "primaryContact": "Первичный контакт",
            "negotiation": "Переговоры",
            "makeDecision": "Принимают решение", 
            "Harmonizationofcontract": "Согласование договора",
            "name": "Наименование",
            "company_id":"Компания",
            "phone" : "Номер телефона", 
            "email" : "email", 
            "user": "Ответственный", 
            "object_id": "объект",
            "created_at": "Дата создания", 
            "updated_at": "Дата обновления",
            "file": "Файл",
            "transactionSource": "Источники сделок",
            "DealsBymanager": "Сделки по менеджерам",
            "purpose": "Цели",
            "SystemUse": "Использование системы за неделю",
            "LatestFiles": "Последние файлы",
            "Salesforecast": "Прогноз продаж",
            "IncomingCalls": "входящие звонки",
            "notes": "Примечаний",
            "outgoingcalls": "исходищие звонки",
            "successfuldeals": "успешные сделки",
            "language": "Язык",
            "lastName": "ФИО",
            "successfullyImplemented": "Успешно реализовано", 
            "closed": "Закрыто и не реализовано",
            "sources": "Источники", 
            "contact": "Контакт",
            "contract": "Сделка",
            "description": "Описание",
            "create":"Создать",
            "cancel": "Отменить",
            "worknumber": "Рабочий телефон",
            "post": "Должность",
            "address":"Адрес", 
            "send": "Отправить",
            "topic":"Тема сообщения", 
            "from" : "От кого",
            "to": "Кому", 
            "date": "Дата",
            "topic2": "Сделка, тема и сообщение",
            "topic3": "Тема",
            "put": "Поставить",
            "calls":"Звонок",
            "meeting": "Встреча",
            "task":"Задача",
            "run_upto": "Выполнить до"





        }
}